{"2024-08-20": {"salaire": 0, "ressources_percues": {}, "cumul": {}}, "2024-08-23": {"salaire": 605132361, "ressources_detail": {"yvahra": {"convois": [0, 0], "exploit": 601200000, "pillage": 0}, "mystogan": {"convois": [0, 0], "exploit": 171687288, "pillage": 0}, "scarapace": {"convois": [0, 0], "exploit": 2170528752, "pillage": 0}, "blackpixel": {"convois": [0, 0], "exploit": 163905168, "pillage": 0}, "antoriax": {"convois": [0, 0], "exploit": 137026728, "pillage": 0}, "bendowin": {"convois": [0, 0], "exploit": 1413911952, "pillage": 0}, "bad_broly": {"convois": [0, 0], "exploit": 132000000, "pillage": 0}, "vikbat": {"convois": [0, 0], "exploit": 50799000, "pillage": 0}}, "cumul": {"antoriax": -468105633, "bad_broly": -473132361, "bendowin": 808779591, "blackpixel": -441227193, "mystogan": -433445073, "scarapace": 1565396391, "vikbat": -554333361, "yvahra": -3932361}}, "2024-08-24": {"salaire": 605132361, "ressources_detail": {"yvahra": {"convois": [0, 0], "exploit": 601200000, "pillage": 0}, "mystogan": {"convois": [0, 0], "exploit": 171687288, "pillage": 0}, "scarapace": {"convois": [0, 0], "exploit": 2170528752, "pillage": 0}, "blackpixel": {"convois": [0, 0], "exploit": 163905168, "pillage": 0}, "antoriax": {"convois": [0, 0], "exploit": 137026728, "pillage": 0}, "bendowin": {"convois": [0, 0], "exploit": 1413911952, "pillage": 0}, "bad_broly": {"convois": [0, 0], "exploit": 132000000, "pillage": 0}, "vikbat": {"convois": [0, 0], "exploit": 50799000, "pillage": 0}}, "cumul": {"antoriax": -468105633, "bad_broly": -473132361, "bendowin": 808779591, "blackpixel": -441227193, "mystogan": -433445073, "scarapace": 1565396391, "vikbat": -554333361, "yvahra": -3932361}}}